pymultidropbus/__init__.py
pymultidropbus/helpers.py
pymultidropbus-0.0.1.dist-info/LICENSE
pymultidropbus-0.0.1.dist-info/METADATA
pymultidropbus-0.0.1.dist-info/WHEEL
pymultidropbus-0.0.1.dist-info/top_level.txt
pymultidropbus-0.0.1.dist-info/RECORD
