Metadata-Version: 2.1
Name: pymultidropbus
Version: 0.0.1
Summary: A Python library that implements a cashless MDB peripheral over UART.
Author: Jaimyn Mayer
Author-email: Jaimyn Mayer <hello@jaimyn.dev>
Project-URL: Homepage, https://github.com/membermatters/pymultidropbus
Project-URL: Issues, https://github.com/membermatters/pymultidropbus/issues
Classifier: Programming Language :: Python :: 3
Classifier: License :: OSI Approved :: MIT License
Classifier: Operating System :: POSIX :: Linux
Requires-Python: >=3.9
License-File: LICENSE
Requires-Dist: pyserial
